iad/__init__.py
iad/errors.py
iad/ratelimit.py
iad/request.py
iad/model/__init__.py
iad/model/client.py
iad/model/upload.py
iad.py-1.0.2.dist-info/LICENSE
iad.py-1.0.2.dist-info/METADATA
iad.py-1.0.2.dist-info/WHEEL
iad.py-1.0.2.dist-info/top_level.txt
iad.py-1.0.2.dist-info/RECORD
