Metadata-Version: 2.1
Name: iad.py
Version: 1.0.2
Summary: A Python Wrapper for the im-a-dev.xyz uploader.
Home-page: https://im-a-dev.xyz/
Author: fxcilities
License: UNKNOWN
Platform: UNKNOWN
Requires-Dist: asyncio
Requires-Dist: aiohttp
